python_statsd-2.0.0.dist-info/DESCRIPTION.rst
python_statsd-2.0.0.dist-info/METADATA
python_statsd-2.0.0.dist-info/RECORD
python_statsd-2.0.0.dist-info/WHEEL
python_statsd-2.0.0.dist-info/metadata.json
python_statsd-2.0.0.dist-info/top_level.txt
statsd/__init__.py
statsd/average.py
statsd/client.py
statsd/compat.py
statsd/connection.py
statsd/counter.py
statsd/gauge.py
statsd/raw.py
statsd/timer.py
