Metadata-Version: 2.0
Name: python-statsd
Version: 2.0.0
Summary: statsd is a client for Etsy's node-js statsd server. A proxy for the Graphite stats collection and graphing server.
Home-page: https://github.com/WoLpH/python-statsd
Author: Rick van Hattem
Author-email: Wolph@wol.ph
License: BSD
Platform: UNKNOWN
Classifier: License :: OSI Approved :: BSD License
